{
  "description": {
    "spec-version": {
      "Right": ">=1.10"
    },
    "package": {
      "name": "authinfo-hs",
      "version": [
        0,
        1,
        0,
        0
      ]
    },
    "license": {
      "Right": "MIT"
    },
    "license-files": [
      "LICENSE"
    ],
    "copyright": "",
    "maintainer": "robgssp@gmail.com",
    "author": "Robert Glossop",
    "stability": "",
    "tested-with": [],
    "homepage": "http://github.com/robgssp/authinfo-hs",
    "pkg-url": "",
    "bug-reports": "",
    "source-repos": [
      {
        "kind": {},
        "type": "Git",
        "location": "git@github.com:robgssp/authinfo-hs.git",
        "module": null,
        "branch": null,
        "tag": null,
        "subdir": null
      }
    ],
    "synopsis": "Password querying for .authinfo",
    "description": "A .authinfo querier",
    "category": "System",
    "custom-fields": [],
    "build-type-raw": "Simple",
    "custom-setup": null,
    "library": null,
    "sublibraries": [],
    "executables": [],
    "foreign-libs": [],
    "test-suites": [],
    "benchmarks": [],
    "data-files": [],
    "data-dir": ".",
    "extra-source-files": [],
    "extra-tmp-files": [],
    "extra-doc-files": []
  },
  "library": {
    "condTreeData": {
      "name": {},
      "exposed-modules": [
        [
          "System",
          "Authinfo"
        ]
      ],
      "re-exported-modules": [],
      "signatures": [],
      "exposed": true,
      "visibility": "LibraryVisibilityPublic",
      "build-info": {
        "buildable": true,
        "buildTools": [],
        "buildToolDepends": [],
        "cppOptions": [],
        "asmOptions": [],
        "cmmOptions": [],
        "ccOptions": [],
        "cxxOptions": [],
        "ldOptions": [],
        "pkgconfigDepends": [],
        "frameworks": [],
        "extraFrameworkDirs": [],
        "asmSources": [],
        "cmmSources": [],
        "cSources": [],
        "cxxSources": [],
        "jsSources": [],
        "hsSourceDirs": [],
        "otherModules": [],
        "virtualModules": [],
        "autogenModules": [],
        "defaultLanguage": "Haskell2010",
        "otherLanguages": [],
        "defaultExtensions": [],
        "otherExtensions": [
          {
            "enable-extension": "OverloadedStrings"
          }
        ],
        "oldExtensions": [],
        "extraLibs": [],
        "extraGHCiLibs": [],
        "extraBundledLibs": [],
        "extraLibFlavours": [],
        "extraDynLibFlavours": [],
        "extraLibDirs": [],
        "includeDirs": [],
        "includes": [],
        "autogenIncludes": [],
        "installIncludes": [],
        "options": [
          [],
          []
        ],
        "profOptions": [
          [],
          []
        ],
        "sharedOptions": [
          [],
          []
        ],
        "staticOptions": [
          [],
          []
        ],
        "customFieldsBI": [],
        "targetBuildDepends": [
          {
            "package-name": "base",
            "version-range": ">=4.7 && <5",
            "library": [
              {}
            ]
          },
          {
            "package-name": "attoparsec",
            "version-range": ">=0.12",
            "library": [
              {}
            ]
          },
          {
            "package-name": "text",
            "version-range": ">=1.1",
            "library": [
              {}
            ]
          },
          {
            "package-name": "network",
            "version-range": ">=2.6",
            "library": [
              {}
            ]
          }
        ],
        "mixins": []
      }
    },
    "condTreeConstraints": [
      {
        "package-name": "base",
        "version-range": ">=4.7 && <5",
        "library": [
          {}
        ]
      },
      {
        "package-name": "attoparsec",
        "version-range": ">=0.12",
        "library": [
          {}
        ]
      },
      {
        "package-name": "text",
        "version-range": ">=1.1",
        "library": [
          {}
        ]
      },
      {
        "package-name": "network",
        "version-range": ">=2.6",
        "library": [
          {}
        ]
      }
    ],
    "condTreeComponents": []
  }
}
