{
  "description": {
    "spec-version": {
      "Right": ">=1.6"
    },
    "package": {
      "name": "hslogger-template",
      "version": [
        0,
        2
      ]
    },
    "license": {
      "Right": "PublicDomain"
    },
    "license-files": [],
    "copyright": "",
    "maintainer": "Brian Lewis <brian@lorf.org>, Ian Taylor <ian@lorf.org>",
    "author": "Brian Lewis <brian@lorf.org>, Ian Taylor <ian@lorf.org>",
    "stability": "",
    "tested-with": [],
    "homepage": "http://github.com/bsl/hslogger-template",
    "pkg-url": "",
    "bug-reports": "",
    "source-repos": [],
    "synopsis": "Automatic generation of hslogger functions",
    "description": "Library for generating hslogger functions using Template Haskell.",
    "category": "Interfaces",
    "custom-fields": [],
    "build-type-raw": "Custom",
    "custom-setup": null,
    "library": null,
    "sublibraries": [],
    "executables": [],
    "foreign-libs": [],
    "test-suites": [],
    "benchmarks": [],
    "data-files": [],
    "data-dir": ".",
    "extra-source-files": [],
    "extra-tmp-files": [],
    "extra-doc-files": []
  },
  "library": {
    "condTreeData": {
      "name": {},
      "exposed-modules": [
        [
          "System",
          "Log",
          "Logger",
          "TH"
        ]
      ],
      "re-exported-modules": [],
      "signatures": [],
      "exposed": true,
      "visibility": "LibraryVisibilityPublic",
      "build-info": {
        "buildable": true,
        "buildTools": [],
        "buildToolDepends": [],
        "cppOptions": [],
        "asmOptions": [],
        "cmmOptions": [],
        "ccOptions": [],
        "cxxOptions": [],
        "ldOptions": [],
        "pkgconfigDepends": [],
        "frameworks": [],
        "extraFrameworkDirs": [],
        "asmSources": [],
        "cmmSources": [],
        "cSources": [],
        "cxxSources": [],
        "jsSources": [],
        "hsSourceDirs": [
          "src"
        ],
        "otherModules": [],
        "virtualModules": [],
        "autogenModules": [],
        "defaultLanguage": null,
        "otherLanguages": [],
        "defaultExtensions": [],
        "otherExtensions": [],
        "oldExtensions": [
          {
            "enable-extension": "TemplateHaskell"
          }
        ],
        "extraLibs": [],
        "extraGHCiLibs": [],
        "extraBundledLibs": [],
        "extraLibFlavours": [],
        "extraDynLibFlavours": [],
        "extraLibDirs": [],
        "includeDirs": [],
        "includes": [],
        "autogenIncludes": [],
        "installIncludes": [],
        "options": [
          [
            "-Wall"
          ],
          []
        ],
        "profOptions": [
          [],
          []
        ],
        "sharedOptions": [
          [],
          []
        ],
        "staticOptions": [
          [],
          []
        ],
        "customFieldsBI": [],
        "targetBuildDepends": [
          {
            "package-name": "base",
            "version-range": "-any",
            "library": [
              {}
            ]
          },
          {
            "package-name": "haskell98",
            "version-range": "-any",
            "library": [
              {}
            ]
          },
          {
            "package-name": "hslogger",
            "version-range": "-any",
            "library": [
              {}
            ]
          },
          {
            "package-name": "template-haskell",
            "version-range": "-any",
            "library": [
              {}
            ]
          }
        ],
        "mixins": []
      }
    },
    "condTreeConstraints": [
      {
        "package-name": "base",
        "version-range": "-any",
        "library": [
          {}
        ]
      },
      {
        "package-name": "haskell98",
        "version-range": "-any",
        "library": [
          {}
        ]
      },
      {
        "package-name": "hslogger",
        "version-range": "-any",
        "library": [
          {}
        ]
      },
      {
        "package-name": "template-haskell",
        "version-range": "-any",
        "library": [
          {}
        ]
      }
    ],
    "condTreeComponents": [
      {
        "condBranchCondition": {
          "variable": {
            "compiler": "GHC",
            "version": ">=6.8"
          }
        },
        "condBranchIfTrue": {
          "condTreeData": {
            "name": {},
            "exposed-modules": [],
            "re-exported-modules": [],
            "signatures": [],
            "exposed": true,
            "visibility": "LibraryVisibilityPublic",
            "build-info": {
              "buildable": true,
              "buildTools": [],
              "buildToolDepends": [],
              "cppOptions": [],
              "asmOptions": [],
              "cmmOptions": [],
              "ccOptions": [],
              "cxxOptions": [],
              "ldOptions": [],
              "pkgconfigDepends": [],
              "frameworks": [],
              "extraFrameworkDirs": [],
              "asmSources": [],
              "cmmSources": [],
              "cSources": [],
              "cxxSources": [],
              "jsSources": [],
              "hsSourceDirs": [],
              "otherModules": [],
              "virtualModules": [],
              "autogenModules": [],
              "defaultLanguage": null,
              "otherLanguages": [],
              "defaultExtensions": [],
              "otherExtensions": [],
              "oldExtensions": [],
              "extraLibs": [],
              "extraGHCiLibs": [],
              "extraBundledLibs": [],
              "extraLibFlavours": [],
              "extraDynLibFlavours": [],
              "extraLibDirs": [],
              "includeDirs": [],
              "includes": [],
              "autogenIncludes": [],
              "installIncludes": [],
              "options": [
                [
                  "-fwarn-tabs"
                ],
                []
              ],
              "profOptions": [
                [],
                []
              ],
              "sharedOptions": [
                [],
                []
              ],
              "staticOptions": [
                [],
                []
              ],
              "customFieldsBI": [],
              "targetBuildDepends": [],
              "mixins": []
            }
          },
          "condTreeConstraints": [],
          "condTreeComponents": []
        }
      }
    ]
  }
}
