{
  "description": {
    "spec-version": {
      "Right": ">=1.10"
    },
    "package": {
      "name": "pinchot",
      "version": [
        0,
        24,
        0,
        0
      ]
    },
    "license": {
      "Right": "BSD3"
    },
    "license-files": [
      "LICENSE"
    ],
    "copyright": "Copyright (c) 2015 - 2017 Omari Norman",
    "maintainer": "omari@smileystation.com",
    "author": "Omari Norman",
    "stability": "Experimental",
    "tested-with": [],
    "homepage": "http://www.github.com/massysett/pinchot",
    "pkg-url": "",
    "bug-reports": "http://www.github.com/massysett/pinchot/issues",
    "source-repos": [
      {
        "kind": {},
        "type": "Git",
        "location": "https://github.com/massysett/pinchot.git",
        "module": null,
        "branch": null,
        "tag": null,
        "subdir": null
      }
    ],
    "synopsis": "Write grammars, not parsers",
    "description": "Please see README.md",
    "category": "Development",
    "custom-fields": [],
    "build-type-raw": "Simple",
    "custom-setup": null,
    "library": null,
    "sublibraries": [],
    "executables": [],
    "foreign-libs": [],
    "test-suites": [],
    "benchmarks": [],
    "data-files": [],
    "data-dir": ".",
    "extra-source-files": [
      "README.md"
    ],
    "extra-tmp-files": [],
    "extra-doc-files": []
  },
  "package-flags": [
    {
      "name": "executables",
      "description": "Build executables",
      "default": false,
      "manual": true
    }
  ],
  "library": {
    "condTreeData": {
      "name": {},
      "exposed-modules": [
        [
          "Pinchot"
        ],
        [
          "Pinchot",
          "Earley"
        ],
        [
          "Pinchot",
          "Examples"
        ],
        [
          "Pinchot",
          "Examples",
          "AllRulesRecord"
        ],
        [
          "Pinchot",
          "Examples",
          "Earley"
        ],
        [
          "Pinchot",
          "Examples",
          "Newman"
        ],
        [
          "Pinchot",
          "Examples",
          "Postal"
        ],
        [
          "Pinchot",
          "Examples",
          "RulesToOptics"
        ],
        [
          "Pinchot",
          "Examples",
          "SyntaxTrees"
        ],
        [
          "Pinchot",
          "Examples",
          "Terminalize"
        ],
        [
          "Pinchot",
          "Locator"
        ],
        [
          "Pinchot",
          "Names"
        ],
        [
          "Pinchot",
          "Pretty"
        ],
        [
          "Pinchot",
          "RecursiveDo"
        ],
        [
          "Pinchot",
          "Rules"
        ],
        [
          "Pinchot",
          "SyntaxTree"
        ],
        [
          "Pinchot",
          "SyntaxTree",
          "Instancer"
        ],
        [
          "Pinchot",
          "SyntaxTree",
          "Optics"
        ],
        [
          "Pinchot",
          "SyntaxTree",
          "Wrappers"
        ],
        [
          "Pinchot",
          "Terminalize"
        ],
        [
          "Pinchot",
          "Types"
        ]
      ],
      "re-exported-modules": [],
      "signatures": [],
      "exposed": true,
      "visibility": "LibraryVisibilityPublic",
      "build-info": {
        "buildable": true,
        "buildTools": [],
        "buildToolDepends": [],
        "cppOptions": [],
        "asmOptions": [],
        "cmmOptions": [],
        "ccOptions": [],
        "cxxOptions": [],
        "ldOptions": [],
        "pkgconfigDepends": [],
        "frameworks": [],
        "extraFrameworkDirs": [],
        "asmSources": [],
        "cmmSources": [],
        "cSources": [],
        "cxxSources": [],
        "jsSources": [],
        "hsSourceDirs": [
          "lib"
        ],
        "otherModules": [],
        "virtualModules": [],
        "autogenModules": [],
        "defaultLanguage": "Haskell2010",
        "otherLanguages": [],
        "defaultExtensions": [],
        "otherExtensions": [
          {
            "enable-extension": "TemplateHaskell"
          }
        ],
        "oldExtensions": [],
        "extraLibs": [],
        "extraGHCiLibs": [],
        "extraBundledLibs": [],
        "extraLibFlavours": [],
        "extraDynLibFlavours": [],
        "extraLibDirs": [],
        "includeDirs": [],
        "includes": [],
        "autogenIncludes": [],
        "installIncludes": [],
        "options": [
          [
            "-W"
          ],
          []
        ],
        "profOptions": [
          [],
          []
        ],
        "sharedOptions": [
          [],
          []
        ],
        "staticOptions": [
          [],
          []
        ],
        "customFieldsBI": [],
        "targetBuildDepends": [
          {
            "package-name": "base",
            "version-range": ">=4.9 && <5",
            "library": [
              {}
            ]
          },
          {
            "package-name": "containers",
            "version-range": ">=0.5.6.2",
            "library": [
              {}
            ]
          },
          {
            "package-name": "transformers",
            "version-range": ">=0.4.2.0",
            "library": [
              {}
            ]
          },
          {
            "package-name": "template-haskell",
            "version-range": ">=2.11",
            "library": [
              {}
            ]
          },
          {
            "package-name": "Earley",
            "version-range": ">=0.11.0.1",
            "library": [
              {}
            ]
          },
          {
            "package-name": "pretty-show",
            "version-range": ">=1.6.9",
            "library": [
              {}
            ]
          },
          {
            "package-name": "lens",
            "version-range": ">=4.13",
            "library": [
              {}
            ]
          },
          {
            "package-name": "semigroups",
            "version-range": ">=0.18.1",
            "library": [
              {}
            ]
          }
        ],
        "mixins": []
      }
    },
    "condTreeConstraints": [
      {
        "package-name": "base",
        "version-range": ">=4.9 && <5",
        "library": [
          {}
        ]
      },
      {
        "package-name": "containers",
        "version-range": ">=0.5.6.2",
        "library": [
          {}
        ]
      },
      {
        "package-name": "transformers",
        "version-range": ">=0.4.2.0",
        "library": [
          {}
        ]
      },
      {
        "package-name": "template-haskell",
        "version-range": ">=2.11",
        "library": [
          {}
        ]
      },
      {
        "package-name": "Earley",
        "version-range": ">=0.11.0.1",
        "library": [
          {}
        ]
      },
      {
        "package-name": "pretty-show",
        "version-range": ">=1.6.9",
        "library": [
          {}
        ]
      },
      {
        "package-name": "lens",
        "version-range": ">=4.13",
        "library": [
          {}
        ]
      },
      {
        "package-name": "semigroups",
        "version-range": ">=0.18.1",
        "library": [
          {}
        ]
      }
    ],
    "condTreeComponents": []
  },
  "executables": {
    "newman": {
      "condTreeData": {
        "name": "newman",
        "module-path": "newman.hs",
        "scope": "public",
        "build-info": {
          "buildable": true,
          "buildTools": [],
          "buildToolDepends": [],
          "cppOptions": [],
          "asmOptions": [],
          "cmmOptions": [],
          "ccOptions": [],
          "cxxOptions": [],
          "ldOptions": [],
          "pkgconfigDepends": [],
          "frameworks": [],
          "extraFrameworkDirs": [],
          "asmSources": [],
          "cmmSources": [],
          "cSources": [],
          "cxxSources": [],
          "jsSources": [],
          "hsSourceDirs": [],
          "otherModules": [],
          "virtualModules": [],
          "autogenModules": [],
          "defaultLanguage": null,
          "otherLanguages": [],
          "defaultExtensions": [],
          "otherExtensions": [],
          "oldExtensions": [],
          "extraLibs": [],
          "extraGHCiLibs": [],
          "extraBundledLibs": [],
          "extraLibFlavours": [],
          "extraDynLibFlavours": [],
          "extraLibDirs": [],
          "includeDirs": [],
          "includes": [],
          "autogenIncludes": [],
          "installIncludes": [],
          "options": [
            [],
            []
          ],
          "profOptions": [
            [],
            []
          ],
          "sharedOptions": [
            [],
            []
          ],
          "staticOptions": [
            [],
            []
          ],
          "customFieldsBI": [],
          "targetBuildDepends": [],
          "mixins": []
        }
      },
      "condTreeConstraints": [],
      "condTreeComponents": [
        {
          "condBranchCondition": {
            "cond_not": {
              "variable": {
                "flag": "executables"
              }
            }
          },
          "condBranchIfTrue": {
            "condTreeData": {
              "name": "newman",
              "module-path": "",
              "scope": "public",
              "build-info": {
                "buildable": false,
                "buildTools": [],
                "buildToolDepends": [],
                "cppOptions": [],
                "asmOptions": [],
                "cmmOptions": [],
                "ccOptions": [],
                "cxxOptions": [],
                "ldOptions": [],
                "pkgconfigDepends": [],
                "frameworks": [],
                "extraFrameworkDirs": [],
                "asmSources": [],
                "cmmSources": [],
                "cSources": [],
                "cxxSources": [],
                "jsSources": [],
                "hsSourceDirs": [],
                "otherModules": [],
                "virtualModules": [],
                "autogenModules": [],
                "defaultLanguage": null,
                "otherLanguages": [],
                "defaultExtensions": [],
                "otherExtensions": [],
                "oldExtensions": [],
                "extraLibs": [],
                "extraGHCiLibs": [],
                "extraBundledLibs": [],
                "extraLibFlavours": [],
                "extraDynLibFlavours": [],
                "extraLibDirs": [],
                "includeDirs": [],
                "includes": [],
                "autogenIncludes": [],
                "installIncludes": [],
                "options": [
                  [],
                  []
                ],
                "profOptions": [
                  [],
                  []
                ],
                "sharedOptions": [
                  [],
                  []
                ],
                "staticOptions": [
                  [],
                  []
                ],
                "customFieldsBI": [],
                "targetBuildDepends": [],
                "mixins": []
              }
            },
            "condTreeConstraints": [],
            "condTreeComponents": []
          },
          "condBranchIfFalse": {
            "condTreeData": {
              "name": "newman",
              "module-path": "",
              "scope": "public",
              "build-info": {
                "buildable": true,
                "buildTools": [],
                "buildToolDepends": [],
                "cppOptions": [],
                "asmOptions": [],
                "cmmOptions": [],
                "ccOptions": [],
                "cxxOptions": [],
                "ldOptions": [],
                "pkgconfigDepends": [],
                "frameworks": [],
                "extraFrameworkDirs": [],
                "asmSources": [],
                "cmmSources": [],
                "cSources": [],
                "cxxSources": [],
                "jsSources": [],
                "hsSourceDirs": [
                  "exe",
                  "lib"
                ],
                "otherModules": [
                  [
                    "Pinchot"
                  ],
                  [
                    "Pinchot",
                    "Earley"
                  ],
                  [
                    "Pinchot",
                    "Examples"
                  ],
                  [
                    "Pinchot",
                    "Examples",
                    "AllRulesRecord"
                  ],
                  [
                    "Pinchot",
                    "Examples",
                    "Earley"
                  ],
                  [
                    "Pinchot",
                    "Examples",
                    "Newman"
                  ],
                  [
                    "Pinchot",
                    "Examples",
                    "Postal"
                  ],
                  [
                    "Pinchot",
                    "Examples",
                    "RulesToOptics"
                  ],
                  [
                    "Pinchot",
                    "Examples",
                    "SyntaxTrees"
                  ],
                  [
                    "Pinchot",
                    "Examples",
                    "Terminalize"
                  ],
                  [
                    "Pinchot",
                    "Locator"
                  ],
                  [
                    "Pinchot",
                    "Names"
                  ],
                  [
                    "Pinchot",
                    "Pretty"
                  ],
                  [
                    "Pinchot",
                    "RecursiveDo"
                  ],
                  [
                    "Pinchot",
                    "Rules"
                  ],
                  [
                    "Pinchot",
                    "SyntaxTree"
                  ],
                  [
                    "Pinchot",
                    "SyntaxTree",
                    "Instancer"
                  ],
                  [
                    "Pinchot",
                    "SyntaxTree",
                    "Optics"
                  ],
                  [
                    "Pinchot",
                    "SyntaxTree",
                    "Wrappers"
                  ],
                  [
                    "Pinchot",
                    "Terminalize"
                  ],
                  [
                    "Pinchot",
                    "Types"
                  ]
                ],
                "virtualModules": [],
                "autogenModules": [],
                "defaultLanguage": "Haskell2010",
                "otherLanguages": [],
                "defaultExtensions": [],
                "otherExtensions": [
                  {
                    "enable-extension": "TemplateHaskell"
                  }
                ],
                "oldExtensions": [],
                "extraLibs": [],
                "extraGHCiLibs": [],
                "extraBundledLibs": [],
                "extraLibFlavours": [],
                "extraDynLibFlavours": [],
                "extraLibDirs": [],
                "includeDirs": [],
                "includes": [],
                "autogenIncludes": [],
                "installIncludes": [],
                "options": [
                  [
                    "-W"
                  ],
                  []
                ],
                "profOptions": [
                  [],
                  []
                ],
                "sharedOptions": [
                  [],
                  []
                ],
                "staticOptions": [
                  [],
                  []
                ],
                "customFieldsBI": [],
                "targetBuildDepends": [
                  {
                    "package-name": "base",
                    "version-range": ">=4.9 && <5",
                    "library": [
                      {}
                    ]
                  },
                  {
                    "package-name": "containers",
                    "version-range": ">=0.5.6.2",
                    "library": [
                      {}
                    ]
                  },
                  {
                    "package-name": "transformers",
                    "version-range": ">=0.4.2.0",
                    "library": [
                      {}
                    ]
                  },
                  {
                    "package-name": "template-haskell",
                    "version-range": ">=2.11",
                    "library": [
                      {}
                    ]
                  },
                  {
                    "package-name": "Earley",
                    "version-range": ">=0.11.0.1",
                    "library": [
                      {}
                    ]
                  },
                  {
                    "package-name": "pretty-show",
                    "version-range": ">=1.6.9",
                    "library": [
                      {}
                    ]
                  },
                  {
                    "package-name": "lens",
                    "version-range": ">=4.13",
                    "library": [
                      {}
                    ]
                  },
                  {
                    "package-name": "semigroups",
                    "version-range": ">=0.18.1",
                    "library": [
                      {}
                    ]
                  }
                ],
                "mixins": []
              }
            },
            "condTreeConstraints": [
              {
                "package-name": "base",
                "version-range": ">=4.9 && <5",
                "library": [
                  {}
                ]
              },
              {
                "package-name": "containers",
                "version-range": ">=0.5.6.2",
                "library": [
                  {}
                ]
              },
              {
                "package-name": "transformers",
                "version-range": ">=0.4.2.0",
                "library": [
                  {}
                ]
              },
              {
                "package-name": "template-haskell",
                "version-range": ">=2.11",
                "library": [
                  {}
                ]
              },
              {
                "package-name": "Earley",
                "version-range": ">=0.11.0.1",
                "library": [
                  {}
                ]
              },
              {
                "package-name": "pretty-show",
                "version-range": ">=1.6.9",
                "library": [
                  {}
                ]
              },
              {
                "package-name": "lens",
                "version-range": ">=4.13",
                "library": [
                  {}
                ]
              },
              {
                "package-name": "semigroups",
                "version-range": ">=0.18.1",
                "library": [
                  {}
                ]
              }
            ],
            "condTreeComponents": []
          }
        }
      ]
    },
    "newmanPretty": {
      "condTreeData": {
        "name": "newmanPretty",
        "module-path": "newmanPretty.hs",
        "scope": "public",
        "build-info": {
          "buildable": true,
          "buildTools": [],
          "buildToolDepends": [],
          "cppOptions": [],
          "asmOptions": [],
          "cmmOptions": [],
          "ccOptions": [],
          "cxxOptions": [],
          "ldOptions": [],
          "pkgconfigDepends": [],
          "frameworks": [],
          "extraFrameworkDirs": [],
          "asmSources": [],
          "cmmSources": [],
          "cSources": [],
          "cxxSources": [],
          "jsSources": [],
          "hsSourceDirs": [],
          "otherModules": [],
          "virtualModules": [],
          "autogenModules": [],
          "defaultLanguage": null,
          "otherLanguages": [],
          "defaultExtensions": [],
          "otherExtensions": [],
          "oldExtensions": [],
          "extraLibs": [],
          "extraGHCiLibs": [],
          "extraBundledLibs": [],
          "extraLibFlavours": [],
          "extraDynLibFlavours": [],
          "extraLibDirs": [],
          "includeDirs": [],
          "includes": [],
          "autogenIncludes": [],
          "installIncludes": [],
          "options": [
            [],
            []
          ],
          "profOptions": [
            [],
            []
          ],
          "sharedOptions": [
            [],
            []
          ],
          "staticOptions": [
            [],
            []
          ],
          "customFieldsBI": [],
          "targetBuildDepends": [],
          "mixins": []
        }
      },
      "condTreeConstraints": [],
      "condTreeComponents": [
        {
          "condBranchCondition": {
            "cond_not": {
              "variable": {
                "flag": "executables"
              }
            }
          },
          "condBranchIfTrue": {
            "condTreeData": {
              "name": "newmanPretty",
              "module-path": "",
              "scope": "public",
              "build-info": {
                "buildable": false,
                "buildTools": [],
                "buildToolDepends": [],
                "cppOptions": [],
                "asmOptions": [],
                "cmmOptions": [],
                "ccOptions": [],
                "cxxOptions": [],
                "ldOptions": [],
                "pkgconfigDepends": [],
                "frameworks": [],
                "extraFrameworkDirs": [],
                "asmSources": [],
                "cmmSources": [],
                "cSources": [],
                "cxxSources": [],
                "jsSources": [],
                "hsSourceDirs": [],
                "otherModules": [],
                "virtualModules": [],
                "autogenModules": [],
                "defaultLanguage": null,
                "otherLanguages": [],
                "defaultExtensions": [],
                "otherExtensions": [],
                "oldExtensions": [],
                "extraLibs": [],
                "extraGHCiLibs": [],
                "extraBundledLibs": [],
                "extraLibFlavours": [],
                "extraDynLibFlavours": [],
                "extraLibDirs": [],
                "includeDirs": [],
                "includes": [],
                "autogenIncludes": [],
                "installIncludes": [],
                "options": [
                  [],
                  []
                ],
                "profOptions": [
                  [],
                  []
                ],
                "sharedOptions": [
                  [],
                  []
                ],
                "staticOptions": [
                  [],
                  []
                ],
                "customFieldsBI": [],
                "targetBuildDepends": [],
                "mixins": []
              }
            },
            "condTreeConstraints": [],
            "condTreeComponents": []
          },
          "condBranchIfFalse": {
            "condTreeData": {
              "name": "newmanPretty",
              "module-path": "",
              "scope": "public",
              "build-info": {
                "buildable": true,
                "buildTools": [],
                "buildToolDepends": [],
                "cppOptions": [],
                "asmOptions": [],
                "cmmOptions": [],
                "ccOptions": [],
                "cxxOptions": [],
                "ldOptions": [],
                "pkgconfigDepends": [],
                "frameworks": [],
                "extraFrameworkDirs": [],
                "asmSources": [],
                "cmmSources": [],
                "cSources": [],
                "cxxSources": [],
                "jsSources": [],
                "hsSourceDirs": [
                  "exe",
                  "lib"
                ],
                "otherModules": [
                  [
                    "Pinchot"
                  ],
                  [
                    "Pinchot",
                    "Earley"
                  ],
                  [
                    "Pinchot",
                    "Examples"
                  ],
                  [
                    "Pinchot",
                    "Examples",
                    "AllRulesRecord"
                  ],
                  [
                    "Pinchot",
                    "Examples",
                    "Earley"
                  ],
                  [
                    "Pinchot",
                    "Examples",
                    "Newman"
                  ],
                  [
                    "Pinchot",
                    "Examples",
                    "Postal"
                  ],
                  [
                    "Pinchot",
                    "Examples",
                    "RulesToOptics"
                  ],
                  [
                    "Pinchot",
                    "Examples",
                    "SyntaxTrees"
                  ],
                  [
                    "Pinchot",
                    "Examples",
                    "Terminalize"
                  ],
                  [
                    "Pinchot",
                    "Locator"
                  ],
                  [
                    "Pinchot",
                    "Names"
                  ],
                  [
                    "Pinchot",
                    "Pretty"
                  ],
                  [
                    "Pinchot",
                    "RecursiveDo"
                  ],
                  [
                    "Pinchot",
                    "Rules"
                  ],
                  [
                    "Pinchot",
                    "SyntaxTree"
                  ],
                  [
                    "Pinchot",
                    "SyntaxTree",
                    "Instancer"
                  ],
                  [
                    "Pinchot",
                    "SyntaxTree",
                    "Optics"
                  ],
                  [
                    "Pinchot",
                    "SyntaxTree",
                    "Wrappers"
                  ],
                  [
                    "Pinchot",
                    "Terminalize"
                  ],
                  [
                    "Pinchot",
                    "Types"
                  ]
                ],
                "virtualModules": [],
                "autogenModules": [],
                "defaultLanguage": "Haskell2010",
                "otherLanguages": [],
                "defaultExtensions": [],
                "otherExtensions": [
                  {
                    "enable-extension": "TemplateHaskell"
                  }
                ],
                "oldExtensions": [],
                "extraLibs": [],
                "extraGHCiLibs": [],
                "extraBundledLibs": [],
                "extraLibFlavours": [],
                "extraDynLibFlavours": [],
                "extraLibDirs": [],
                "includeDirs": [],
                "includes": [],
                "autogenIncludes": [],
                "installIncludes": [],
                "options": [
                  [
                    "-W"
                  ],
                  []
                ],
                "profOptions": [
                  [],
                  []
                ],
                "sharedOptions": [
                  [],
                  []
                ],
                "staticOptions": [
                  [],
                  []
                ],
                "customFieldsBI": [],
                "targetBuildDepends": [
                  {
                    "package-name": "base",
                    "version-range": ">=4.9 && <5",
                    "library": [
                      {}
                    ]
                  },
                  {
                    "package-name": "containers",
                    "version-range": ">=0.5.6.2",
                    "library": [
                      {}
                    ]
                  },
                  {
                    "package-name": "transformers",
                    "version-range": ">=0.4.2.0",
                    "library": [
                      {}
                    ]
                  },
                  {
                    "package-name": "template-haskell",
                    "version-range": ">=2.11",
                    "library": [
                      {}
                    ]
                  },
                  {
                    "package-name": "Earley",
                    "version-range": ">=0.11.0.1",
                    "library": [
                      {}
                    ]
                  },
                  {
                    "package-name": "pretty-show",
                    "version-range": ">=1.6.9",
                    "library": [
                      {}
                    ]
                  },
                  {
                    "package-name": "lens",
                    "version-range": ">=4.13",
                    "library": [
                      {}
                    ]
                  },
                  {
                    "package-name": "semigroups",
                    "version-range": ">=0.18.1",
                    "library": [
                      {}
                    ]
                  }
                ],
                "mixins": []
              }
            },
            "condTreeConstraints": [
              {
                "package-name": "base",
                "version-range": ">=4.9 && <5",
                "library": [
                  {}
                ]
              },
              {
                "package-name": "containers",
                "version-range": ">=0.5.6.2",
                "library": [
                  {}
                ]
              },
              {
                "package-name": "transformers",
                "version-range": ">=0.4.2.0",
                "library": [
                  {}
                ]
              },
              {
                "package-name": "template-haskell",
                "version-range": ">=2.11",
                "library": [
                  {}
                ]
              },
              {
                "package-name": "Earley",
                "version-range": ">=0.11.0.1",
                "library": [
                  {}
                ]
              },
              {
                "package-name": "pretty-show",
                "version-range": ">=1.6.9",
                "library": [
                  {}
                ]
              },
              {
                "package-name": "lens",
                "version-range": ">=4.13",
                "library": [
                  {}
                ]
              },
              {
                "package-name": "semigroups",
                "version-range": ">=0.18.1",
                "library": [
                  {}
                ]
              }
            ],
            "condTreeComponents": []
          }
        }
      ]
    }
  }
}
