{
  "description": {
    "spec-version": {
      "Right": ">=1.10"
    },
    "package": {
      "name": "dtw",
      "version": [
        1,
        0,
        3,
        0
      ]
    },
    "license": {
      "Right": "MIT"
    },
    "license-files": [
      "LICENSE"
    ],
    "copyright": "",
    "maintainer": "fho@f12n.de",
    "author": "Florian Hofmann",
    "stability": "",
    "tested-with": [],
    "homepage": "",
    "pkg-url": "",
    "bug-reports": "",
    "source-repos": [
      {
        "kind": {},
        "type": "Git",
        "location": "https://github.com/fhaust/dtw",
        "module": null,
        "branch": null,
        "tag": null,
        "subdir": null
      }
    ],
    "synopsis": "(Fast) Dynamic Time Warping",
    "description": "This package implements dynamic time warping as described\nhere <http://en.wikipedia.org/w/index.php?title=Dynamic_time_warping>",
    "category": "Algorithms, Data mining, Machine learning",
    "custom-fields": [],
    "build-type-raw": "Simple",
    "custom-setup": null,
    "library": null,
    "sublibraries": [],
    "executables": [],
    "foreign-libs": [],
    "test-suites": [],
    "benchmarks": [],
    "data-files": [],
    "data-dir": ".",
    "extra-source-files": [],
    "extra-tmp-files": [],
    "extra-doc-files": []
  },
  "library": {
    "condTreeData": {
      "name": {},
      "exposed-modules": [
        [
          "Data",
          "DTW"
        ]
      ],
      "re-exported-modules": [],
      "signatures": [],
      "exposed": true,
      "visibility": "LibraryVisibilityPublic",
      "build-info": {
        "buildable": true,
        "buildTools": [],
        "buildToolDepends": [],
        "cppOptions": [],
        "asmOptions": [],
        "cmmOptions": [],
        "ccOptions": [],
        "cxxOptions": [],
        "ldOptions": [],
        "pkgconfigDepends": [],
        "frameworks": [],
        "extraFrameworkDirs": [],
        "asmSources": [],
        "cmmSources": [],
        "cSources": [],
        "cxxSources": [],
        "jsSources": [],
        "hsSourceDirs": [
          "src"
        ],
        "otherModules": [],
        "virtualModules": [],
        "autogenModules": [],
        "defaultLanguage": "Haskell2010",
        "otherLanguages": [],
        "defaultExtensions": [],
        "otherExtensions": [],
        "oldExtensions": [],
        "extraLibs": [],
        "extraGHCiLibs": [],
        "extraBundledLibs": [],
        "extraLibFlavours": [],
        "extraDynLibFlavours": [],
        "extraLibDirs": [],
        "includeDirs": [],
        "includes": [],
        "autogenIncludes": [],
        "installIncludes": [],
        "options": [
          [
            "-Wall"
          ],
          []
        ],
        "profOptions": [
          [],
          []
        ],
        "sharedOptions": [
          [],
          []
        ],
        "staticOptions": [
          [],
          []
        ],
        "customFieldsBI": [],
        "targetBuildDepends": [
          {
            "package-name": "base",
            "version-range": ">=4.6 && <4.10",
            "library": [
              {}
            ]
          },
          {
            "package-name": "vector",
            "version-range": ">=0.10 && <0.12",
            "library": [
              {}
            ]
          },
          {
            "package-name": "vector-space",
            "version-range": ">=0.9 && <0.11",
            "library": [
              {}
            ]
          },
          {
            "package-name": "containers",
            "version-range": ">=0.5 && <0.6",
            "library": [
              {}
            ]
          }
        ],
        "mixins": []
      }
    },
    "condTreeConstraints": [
      {
        "package-name": "base",
        "version-range": ">=4.6 && <4.10",
        "library": [
          {}
        ]
      },
      {
        "package-name": "vector",
        "version-range": ">=0.10 && <0.12",
        "library": [
          {}
        ]
      },
      {
        "package-name": "vector-space",
        "version-range": ">=0.9 && <0.11",
        "library": [
          {}
        ]
      },
      {
        "package-name": "containers",
        "version-range": ">=0.5 && <0.6",
        "library": [
          {}
        ]
      }
    ],
    "condTreeComponents": []
  },
  "test-suites": {
    "maintest": {
      "condTreeData": {
        "name": "",
        "interface": {
          "version": [
            1,
            0
          ],
          "filepath": "MainTest.hs"
        },
        "build-info": {
          "buildable": true,
          "buildTools": [],
          "buildToolDepends": [],
          "cppOptions": [],
          "asmOptions": [],
          "cmmOptions": [],
          "ccOptions": [],
          "cxxOptions": [],
          "ldOptions": [],
          "pkgconfigDepends": [],
          "frameworks": [],
          "extraFrameworkDirs": [],
          "asmSources": [],
          "cmmSources": [],
          "cSources": [],
          "cxxSources": [],
          "jsSources": [],
          "hsSourceDirs": [
            "src",
            "test",
            "src"
          ],
          "otherModules": [],
          "virtualModules": [],
          "autogenModules": [],
          "defaultLanguage": "Haskell2010",
          "otherLanguages": [],
          "defaultExtensions": [],
          "otherExtensions": [],
          "oldExtensions": [],
          "extraLibs": [],
          "extraGHCiLibs": [],
          "extraBundledLibs": [],
          "extraLibFlavours": [],
          "extraDynLibFlavours": [],
          "extraLibDirs": [],
          "includeDirs": [],
          "includes": [],
          "autogenIncludes": [],
          "installIncludes": [],
          "options": [
            [
              "-O2",
              "-Wall"
            ],
            []
          ],
          "profOptions": [
            [],
            []
          ],
          "sharedOptions": [
            [],
            []
          ],
          "staticOptions": [
            [],
            []
          ],
          "customFieldsBI": [],
          "targetBuildDepends": [
            {
              "package-name": "base",
              "version-range": "-any",
              "library": [
                {}
              ]
            },
            {
              "package-name": "vector",
              "version-range": "-any",
              "library": [
                {}
              ]
            },
            {
              "package-name": "vector-space",
              "version-range": "-any",
              "library": [
                {}
              ]
            },
            {
              "package-name": "thyme",
              "version-range": "-any",
              "library": [
                {}
              ]
            },
            {
              "package-name": "containers",
              "version-range": "-any",
              "library": [
                {}
              ]
            },
            {
              "package-name": "test-framework",
              "version-range": "-any",
              "library": [
                {}
              ]
            },
            {
              "package-name": "test-framework-quickcheck2",
              "version-range": "-any",
              "library": [
                {}
              ]
            },
            {
              "package-name": "QuickCheck",
              "version-range": "-any",
              "library": [
                {}
              ]
            }
          ],
          "mixins": []
        }
      },
      "condTreeConstraints": [
        {
          "package-name": "base",
          "version-range": "-any",
          "library": [
            {}
          ]
        },
        {
          "package-name": "vector",
          "version-range": "-any",
          "library": [
            {}
          ]
        },
        {
          "package-name": "vector-space",
          "version-range": "-any",
          "library": [
            {}
          ]
        },
        {
          "package-name": "thyme",
          "version-range": "-any",
          "library": [
            {}
          ]
        },
        {
          "package-name": "containers",
          "version-range": "-any",
          "library": [
            {}
          ]
        },
        {
          "package-name": "test-framework",
          "version-range": "-any",
          "library": [
            {}
          ]
        },
        {
          "package-name": "test-framework-quickcheck2",
          "version-range": "-any",
          "library": [
            {}
          ]
        },
        {
          "package-name": "QuickCheck",
          "version-range": "-any",
          "library": [
            {}
          ]
        }
      ],
      "condTreeComponents": []
    }
  }
}
